pkg/app.py
pkg/args.py
pkg/sample.py
pkg/test_app.py
jigar-0.0.3.dist-info/LICENSE
jigar-0.0.3.dist-info/METADATA
jigar-0.0.3.dist-info/WHEEL
jigar-0.0.3.dist-info/top_level.txt
jigar-0.0.3.dist-info/RECORD
