Metadata-Version: 2.1
Name: jigar
Version: 0.0.3
Summary: A [simple] [general-purpose] Python template 🐍🚀🎉🦕
Author-email: Mohsen Hariri <mhariri68@gmail.com>
License: GPL-3.0 License
Keywords: Boilerplate,Template
Classifier: Programming Language :: Python :: 3.8
Classifier: License :: OSI Approved :: GNU General Public License v3 or later (GPLv3+)
Classifier: Operating System :: OS Independent
Requires-Python: >=3.6
License-File: LICENSE
Requires-Dist: importlib-metadata ; python_version < "3.8"
